cord/__init__.py
encord/__init__.py
encord/client.py
encord/configs.py
encord/constants/__init__.py
encord/constants/enums.py
encord/constants/model.py
encord/constants/model_weights.py
encord/constants/string_constants.py
encord/exceptions.py
encord/http/__init__.py
encord/http/error_utils.py
encord/http/querier.py
encord/http/query_methods.py
encord/http/request.py
encord/http/utils.py
encord/orm/__init__.py
encord/orm/api_key.py
encord/orm/base_orm.py
encord/orm/cloud_integration.py
encord/orm/dataset.py
encord/orm/dataset_with_user_role.py
encord/orm/formatter.py
encord/orm/label_log.py
encord/orm/label_row.py
encord/orm/labeling_algorithm.py
encord/orm/model.py
encord/orm/project.py
encord/orm/project_api_key.py
encord/orm/project_with_user_role.py
encord/orm/tests/test_create_dataset_response.py
encord/orm/tests/test_dataset.py
encord/project_ontology/__init__.py
encord/project_ontology/classification_attribute.py
encord/project_ontology/classification_option.py
encord/project_ontology/classification_type.py
encord/project_ontology/object_type.py
encord/project_ontology/ontology.py
encord/project_ontology/ontology_classification.py
encord/project_ontology/ontology_object.py
encord/user_client.py
encord/utilities/__init__.py
encord/utilities/client_utilities.py
encord/utilities/label_utilities.py
encord/utilities/project_user.py
cord_client_python-0.1.34.dist-info/LICENSE
cord_client_python-0.1.34.dist-info/WHEEL
cord_client_python-0.1.34.dist-info/METADATA
cord_client_python-0.1.34.dist-info/RECORD
