Metadata-Version: 2.1
Name: cord-client-python
Version: 0.1.34
Summary: Cord Python SDK Client
Home-page: https://github.com/cord-team/cord-client-python
License: Apache Software License
Keywords: cord,encord
Author: Cord Technologies Limited
Author-email: hello@cord.tech
Requires-Python: >=3.7,<4.0
Classifier: License :: OSI Approved :: Apache Software License
Classifier: License :: Other/Proprietary License
Classifier: Operating System :: OS Independent
Classifier: Programming Language :: Python :: 3
Classifier: Programming Language :: Python :: 3.10
Classifier: Programming Language :: Python :: 3.7
Classifier: Programming Language :: Python :: 3.8
Classifier: Programming Language :: Python :: 3.9
Requires-Dist: cryptography (>=3.4.8,<4.0.0)
Requires-Dist: python-dateutil (>=2.8.2,<3.0.0)
Requires-Dist: requests (==2.25.0)
Requires-Dist: tqdm (>=4.32.1,<5.0.0)
Requires-Dist: uuid (>=1.30,<2.0)
Project-URL: Documentation, https://docs.cord.tech/docs/client
Project-URL: Repository, https://github.com/cord-team/cord-client-python
